antchain_sdk_ak_bb3e5638866e4c77aa9ae8ac5c14e933/__init__.py
antchain_sdk_ak_bb3e5638866e4c77aa9ae8ac5c14e933/client.py
antchain_sdk_ak_bb3e5638866e4c77aa9ae8ac5c14e933/models.py
antchain_ak_bb3e5638866e4c77aa9ae8ac5c14e933-1.0.5.dist-info/LICENSE
antchain_ak_bb3e5638866e4c77aa9ae8ac5c14e933-1.0.5.dist-info/METADATA
antchain_ak_bb3e5638866e4c77aa9ae8ac5c14e933-1.0.5.dist-info/WHEEL
antchain_ak_bb3e5638866e4c77aa9ae8ac5c14e933-1.0.5.dist-info/top_level.txt
antchain_ak_bb3e5638866e4c77aa9ae8ac5c14e933-1.0.5.dist-info/RECORD
